shellxec/__init__.py
shellxec/_core/__init__.py
shellxec/_core/_core.py
test/__init__.py
test/test_shellxec.py
shellxec-0.1.9.dist-info/METADATA
shellxec-0.1.9.dist-info/WHEEL
shellxec-0.1.9.dist-info/top_level.txt
shellxec-0.1.9.dist-info/RECORD
