Metadata-Version: 2.1
Name: shellxec
Version: 0.1.9
